py4colors/__init__.py
py4colors/py4colors.py
py4colors-1.5.6.dist-info/METADATA
py4colors-1.5.6.dist-info/WHEEL
py4colors-1.5.6.dist-info/top_level.txt
py4colors-1.5.6.dist-info/RECORD
