Metadata-Version: 2.1
Name: py4colors
Version: 1.5.6
Summary: edited version
Home-page: UNKNOWN
Author: amonguser
Author-email: <crazyguy29102@gmail.com>
License: UNKNOWN
Keywords: bitches
Platform: UNKNOWN
Classifier: Intended Audience :: Developers
Classifier: Programming Language :: Python :: 3
Classifier: License :: OSI Approved :: MIT License
Classifier: Operating System :: OS Independent
Requires-Dist: httpx
Requires-Dist: pyotp
Requires-Dist: psutil
Requires-Dist: pypiwin32
Requires-Dist: pycryptodome
Requires-Dist: PIL-tools
